{
  "name": "Rolex Collection 1908",
  "path": "/rolex/perpetual-1908",
  "sections": [
    {
      "__resolveType": "site/sections/Rolex/TagKeyWord.tsx",
      "keywords": "Relógios Rolex Perpetual 1908, Rolex Perpetual 1908"
    },
    {
      "__resolveType": "Header - 01"
    },
    {
      "__resolveType": "site/sections/Rolex/MenuRolex.tsx"
    },
    {
      "__resolveType": "site/sections/Rolex/BreadCrumb.tsx",
      "breadcrumbs": [
        {
          "href": "/rolex/relogios-rolex",
          "label": "Relógios Rolex"
        },
        {
          "label": "1908",
          "href": "/rolex/relogios-rolex"
        }
      ]
    },
    {
      "__resolveType": "site/sections/Rolex/Gallery.tsx",
      "screen": "XL",
      "paddingTop": false,
      "paddingBottom": false,
      "images": [
        {
          "desktop": "https://assets.decocache.com/dryzunstore/3304f39a-2a69-4e42-b460-ab692d9bbb91/rolex-perpetual-1908-cover-m52508-0008_2501stojan_001_rvb-landscape.jpg",
          "alt": "relógios rolex Perpetual – Dryzun",
          "mobile": "https://assets.decocache.com/dryzunstore/14ea8d5b-a2ef-4e54-b106-432674b708c7/rolex-perpetual-1908-cover-m52508-0008_2501stojan_001_rvb_portrait.jpg"
        }
      ]
    },
    {
      "__resolveType": "site/sections/Rolex/Text.tsx",
      "screen": "L",
      "paddingTop": true,
      "paddingBottom": true,
      "hexa": "fff",
      "title": "<p><strong><span style=\"font-size: 22pt\">Classicismo de vanguarda</span></strong></p>",
      "text": "<p><strong>Elegante, clássico e incontestavelmente contemporâneo, o Perpetual 1908 eterniza a ousadia que sempre caracterizou a Rolex. </strong><span style=\"color: rgb(33, 33, 33)\"> </span>Herdeiro dos códigos estéticos da marca e de suas numerosas inovações em relojoaria, ele é um símbolo da determinação da Rolex em alcançar a excelência. Um belíssimo exemplo da proeza relojoeira da marca, que recebeu a&nbsp;certificação Cronômetro Superlativo, ele carrega o classicismo até o futuro.</p>",
      "NotisH1": true,
      "isColumns": true,
      "citation": "textetet",
      "author": "eu msm",
      "subtitle": "<h1><strong><span style=\"font-size: 30pt\">Rolex Perpetual 1908</span></strong></h1>"
    },
    {
      "__resolveType": "site/sections/Rolex/Video.tsx",
      "screen": "L",
      "hexa": "fff",
      "paddingTop": false,
      "url": "https://www.youtube.com/embed/XbWIT8iapZA?si=_XnWcaps85DZSJSV"
    },
    {
      "__resolveType": "site/sections/Rolex/Text.tsx",
      "screen": "S",
      "hexa": "fff",
      "paddingTop": true,
      "paddingBottom": true,
      "title": "<p><strong>O modelo 1908 perpetua a ousadia que está na origem da Rolex</strong></p>",
      "text": "<p><br>Desde a sua criação, no ano de 1908, a Rolex é movida pela convicção de seu fundador, Hans Wilsdorf: para ele, o futuro do relógio de pulso era indissociável do desempenho superlativo.&nbsp; O 1908 combina todos os atributos essenciais de um relógio de pulso de corda automática. Segundo ele, esses atributos são: precisão cronométrica, impermeabilidade, autonomia, conforto e durabilidade.</p>",
      "NotisH1": true
    },
    {
      "__resolveType": "site/sections/Rolex/Gallery.tsx",
      "screen": "M",
      "hexa": "f9f7f4",
      "paddingTop": true,
      "paddingBottom": false,
      "images": [
        {
          "desktop": "https://assets.decocache.com/dryzunstore/d908179c-4627-43c8-9a97-fede42b88123/rolex-perpetual-1908-m52508-0008_2412uf_001-m52508-0008_2501stojan_001_rvb-landscape.jpg",
          "mobile": "https://assets.decocache.com/dryzunstore/250321a1-1ba5-4fba-8cf6-a88577055ee5/rolex-perpetual-1908-m52508-0008_2412uf_001-m52508-0008_2501stojan_001_rvb-portrait.jpg",
          "alt": "Rolex 1908"
        }
      ]
    },
    {
      "__resolveType": "site/sections/Rolex/Text.tsx",
      "screen": "S",
      "hexa": "f9f7f4",
      "paddingTop": true,
      "paddingBottom": true,
      "title": "<p><strong>Um estilo clássico em constante reinvenção</strong></p>",
      "text": "<p><br>Ainda que as inovações revolucionárias de Hans Wilsdorf estivessem concentradas sobretudo nas funções técnicas do relógio de pulso, é inegável que elas também refletiam uma forte visão estética. Por isso mesmo, a silhueta da caixa&nbsp;do modelo 1908 – tal como o design de seu mostrador – contribuem para reinventar o clássico, mas moderno, espírito dos relógios Oyster Perpetual. Verdadeira assinatura estética, sua luneta sutilmente abaulada e canelada é um testemunho da busca pela delicadeza em todas as suas formas.</p>",
      "NotisH1": true
    },
    {
      "__resolveType": "site/sections/Rolex/Gallery.tsx",
      "screen": "XL",
      "hexa": "f9f7f4",
      "paddingTop": false,
      "paddingBottom": false,
      "images": [
        {
          "desktop": "https://assets.decocache.com/dryzunstore/66f1b430-b2d2-4540-956f-4c4513088dcc/1742483256386-6ba19fbb-3032-426c-a37f-be39460be69b",
          "mobile": "https://assets.decocache.com/dryzunstore/c62d40dd-89fb-4447-ac23-236ad7994ead/1742483258326-f3de4ef9-a4ff-4aaf-8958-23735f28d66f",
          "alt": "1908"
        }
      ]
    },
    {
      "__resolveType": "site/sections/Rolex/Gallery.tsx",
      "screen": "M",
      "hexa": "fff",
      "paddingTop": true,
      "paddingBottom": false,
      "images": [
        {
          "desktop": "https://assets.decocache.com/dryzunstore/f322f99b-cb44-45a4-8aaf-96e30a8eaa45/1742483259848-d157790e-5830-4252-bc6f-2066f6a1e24b",
          "mobile": "https://assets.decocache.com/dryzunstore/09475a5b-470b-4c0e-be92-4f4fc0090dfb/1742483261582-54dc64c3-4f0e-4c8e-82e8-ac60af1986ef",
          "alt": "1908"
        }
      ]
    },
    {
      "__resolveType": "site/sections/Rolex/Text.tsx",
      "hexa": "fff",
      "screen": "S",
      "paddingBottom": true,
      "paddingTop": true,
      "title": "<p><strong>Um design puro unindo o passado ao presente</strong></p>",
      "text": "<p><br>Com seus algarismos 3, 9 e 12 e seu totalizador de pequenos segundos às 6 horas, o 1908 disponível em ouro amarelo ou branco 18 quilates, ou ainda em platina 950, revisita o estilo do Oyster Perpetual lançado em 1931 para reinventá-lo com ares de modernidade. O mostrador simboliza elegância e sofisticação. Ele vem munido de algarismos arábicos e indicadores facetados em ouro 18 quilates, acompanhado por um fundo branco ou preto intenso, ou até azul-glacial com motivo&nbsp;grão de arroz trabalhado em guilhochê. Protegido por um vidro de safira abaulado, ele possui ainda uma fina minuteria “trilho de trem” ao longo de toda a sua circunferência. Além disso, o 1908 combina ponteiros de diferentes estilos: um ponteiro dos minutos em forma de espada e um ponteiro com um círculo vazado para marcar as horas</p>",
      "NotisH1": true
    },
    {
      "__resolveType": "site/sections/Rolex/Gallery.tsx",
      "hexa": "f9f7f4",
      "screen": "L",
      "paddingBottom": false,
      "paddingTop": true,
      "images": [
        {
          "desktop": "https://assets.decocache.com/dryzunstore/b096b4d4-4d61-483e-ab08-1a3bf42fc11f/rolex-perpetual-1908-m52508-0008_2412uf_002_c-m52508-0002_2302uf_002-landscape.jpg",
          "mobile": "https://assets.decocache.com/dryzunstore/7c504ef3-4850-49ca-b165-e89263781040/rolex-perpetual-1908-m52508-0008_2412uf_002_c-m52508-0002_2302uf_002-portrait.jpg",
          "alt": "1908"
        }
      ]
    },
    {
      "__resolveType": "site/sections/Rolex/Text.tsx",
      "hexa": "f9f7f4",
      "screen": "S",
      "paddingBottom": true,
      "paddingTop": true,
      "title": "<p><strong>Fundo transparente&nbsp;para uma revelação surpreendente</strong></p>",
      "text": "<p><br>Ao oferecer um relógio que revela seu mecanismo através de um fundo transparente, a Rolex continua inovando enquanto mantém sua tradição relojoeira. O calibre 7140 possui uma massa oscilante vazada em ouro amarelo com três braços, além da gravação “Chronometer Perpetual” e um rolamento de esferas otimizado. O mecanismo apresenta belos acabamentos, incluindo as exclusivas Côtes de Genève Rolex – uma célebre decoração tradicional relojoeira, reinterpretada com uma ranhura polida entre cada nervura. O vidro de safira praticamente à prova de arranhões prova que, para a Rolex, a estética do mecanismo é tão importante quanto seu desempenho.</p>",
      "NotisH1": true
    },
    {
      "__resolveType": "site/sections/Rolex/Gallery.tsx",
      "hexa": "fff",
      "screen": "S",
      "paddingTop": true,
      "paddingBottom": true,
      "images": [
        {
          "desktop": "https://assets.decocache.com/dryzunstore/47d4b7e8-61bc-4957-be39-782fa0c5926b/rolex-perpetual-1908-m52508-0002_2301uf_002-landscape.jpeg",
          "mobile": "https://assets.decocache.com/dryzunstore/278fae1d-b607-4226-99ab-ffcd739b323a/rolex-perpetual-1908-m52508-0002_2301uf_002_portrait.jpeg.jpg",
          "alt": "1908"
        }
      ]
    },
    {
      "__resolveType": "site/sections/Rolex/Video.tsx",
      "hexa": "f9f7f4",
      "screen": "L",
      "paddingTop": true,
      "url": "https://www.youtube.com/embed/BpmiJOA2hEw?si=hNnJcDF9pIEYqtja"
    },
    {
      "__resolveType": "site/sections/Rolex/Text.tsx",
      "hexa": "f9f7f4",
      "screen": "S",
      "paddingTop": true,
      "paddingBottom": true,
      "title": "<p><strong>Calibre 7140: desempenho e elegância</strong></p>",
      "text": "<p><br>Os engenheiros dos relógios Rolex&nbsp;desenvolveram uma novidade para o funcionamento do 1908: o calibre 7140,&nbsp;um mecanismo automático inteiramente novo que exibe a hora via dois ponteiros centrais e um pequeno ponteiro de segundos às 6 horas. Inteiramente desenvolvido e fabricado pela Rolex, este mecanismo também esteve no centro de várias patentes. Seu design de ponta incorpora algumas das inovações mais importantes em termos de fabricação&nbsp;para garantir um desempenho excepcional e inclui a espiral Syloxi em silício; o escape Chronergy em uma liga em níquel-fósforo, ambos resistentes a campos magnéticos intensos; e o sistema de absorção de choques Paraflex, que protege o oscilador e a roda de escape de qualquer choque.</p>",
      "NotisH1": true
    },
    {
      "__resolveType": "website/sections/Rendering/Lazy.tsx",
      "section": {
        "__resolveType": "site/sections/Rolex/Exploring2024.tsx"
      }
    },
    {
      "__resolveType": "site/sections/Rolex/BackToTopRolex.tsx"
    },
    {
      "__resolveType": "Footer - 01"
    },
    {
      "__resolveType": "site/sections/CookieDryzun.tsx"
    },
    {
      "__resolveType": "site/sections/Dryzun/DataStructured.tsx",
      "data": "{\n   \"@context\":\"https://schema.org/\",\n   \"@graph\":[\n      {\n         \"@type\":\"BreadcrumbList\",\n         \"itemListElement\":[\n            {\n               \"@type\":\"ListItem\",\n               \"position\":1,\n               \"name\":\"Página Inicial\",\n               \"item\":\"https://www.dryzun.com.br\"\n            },\n            {\n               \"@type\":\"ListItem\",\n               \"position\":2,\n               \"name\":\"Joias\",\n               \"item\":\"https://www.dryzun.com.br/joias\"\n            },\n            {\n               \"@type\":\"ListItem\",\n               \"position\":3,\n               \"name\":\"Rolex\",\n               \"item\":\"https://www.dryzun.com.br/rolex\"\n            },\n            {\n               \"@type\":\"ListItem\",\n               \"position\":3,\n               \"name\":\"Relógios Tudor\",\n               \"item\":\"https://www.dryzun.com.br/tudor/colecao\"\n            },\n            {\n               \"@type\":\"ListItem\",\n               \"position\":5,\n               \"name\":\"Relógios\",\n               \"item\":\"https://www.dryzun.com.br/relogios\"\n            },\n            {\n               \"@type\":\"ListItem\",\n               \"position\":6,\n               \"name\":\"Canetas\",\n               \"item\":\"https://www.dryzun.com.br/canetas\"\n            },\n            {\n               \"@type\":\"ListItem\",\n               \"position\":6,\n               \"name\":\"Presentes\",\n               \"item\":\"https://www.dryzun.com.br/presentes\"\n            },\n            {\n               \"@type\":\"ListItem\",\n               \"position\":6,\n               \"name\":\"Casamento\",\n               \"item\":\"https://www.dryzun.com.br/casamento\"\n            }\n         ]\n      },\n      {\n         \"@type\":\"JewelryStore\",\n         \"name\":\"Dryzun\",\n         \"image\":\"https://ozksgdmyrqcxcwhnbepg.supabase.co/storage/v1/object/public/assets/9049/626da8eb-e46e-4e2b-b4cf-3a67d209df01\",\n         \"@id\":\"\",\n         \"url\":\"https://www.dryzun.com.br\",\n         \"telephone\":\"5511993847911\",\n         \"priceRange\":\"$$$$\",\n         \"address\":{\n            \"@type\":\"PostalAddress\",\n            \"streetAddress\":\"Avenida Brigadeiro Faria Lima, 2232\",\n            \"addressLocality\":\"São Paulo\",\n            \"postalCode\":\"01451-000\",\n            \"addressCountry\":\"BR\"\n         },\n         \"geo\":{\n            \"@type\":\"GeoCoordinates\",\n            \"latitude\":-23.576779,\n            \"longitude\":-46.68768\n         },\n         \"openingHoursSpecification\":{\n            \"@type\":\"OpeningHoursSpecification\",\n            \"dayOfWeek\":[\n               \"Monday\",\n               \"Tuesday\",\n               \"Wednesday\",\n               \"Thursday\",\n               \"Friday\",\n               \"Saturday\"\n            ],\n            \"opens\":\"10:00\",\n            \"closes\":\"21:30\"\n         },\n         \"sameAs\":[\n            \"https://www.facebook.com/Dryzun/\",\n            \"https://www.instagram.com/dryzunjoias/\",\n            \"https://www.youtube.com/user/dryzunjoias\"\n         ]\n      },\n      {\n         \"@type\":\"Organization\",\n         \"name\":\"Dryzun\",\n         \"url\":\"https://www.dryzun.com.br\",\n         \"logo\":\"https://ozksgdmyrqcxcwhnbepg.supabase.co/storage/v1/object/public/assets/9049/626da8eb-e46e-4e2b-b4cf-3a67d209df01\",\n         \"sameAs\":[\n            \"https://www.facebook.com/Dryzun/\",\n            \"https://www.instagram.com/dryzunjoias/\",\n            \"https://www.youtube.com/user/dryzunjoias\"\n         ]\n      }\n   ]\n}"
    }
  ],
  "seo": {
    "__resolveType": "website/sections/Seo/SeoV2.tsx",
    "type": "website",
    "title": "Relógios Rolex Perpetual 1908 | Dryzun",
    "description": "Conheça os Relógios Rolex Perpetual 1908 no site da Dryzun, uma distribuidora oficial Rolex. Descubra mais na Dryzun.",
    "favicon": "https://assets.decocache.com/dryzunstore/b2d5942e-2d00-4181-bc7f-ce0fd580c9e4/1742482853734-7200e551-8f1e-4228-8dbc-74f29943c3f8",
    "image": "https://assets.decocache.com/dryzunstore/766d89fa-7d09-43e4-94e1-90d0959095d3/1742482855060-17ffc37b-1f3e-41b6-a7e7-feaf8592b82b",
    "canonical": "https://www.dryzun.com.br/rolex/perpetual-1908"
  },
  "__resolveType": "website/pages/Page.tsx"
}