{
  "name": "Rolex Collection Day-Date",
  "path": "/rolex/day-date",
  "sections": [
    {
      "__resolveType": "site/sections/Rolex/TagKeyWord.tsx",
      "keywords": "Relógios Rolex DAY, Rolex Day-Date"
    },
    {
      "__resolveType": "Header - 01"
    },
    {
      "__resolveType": "site/sections/Rolex/MenuRolex.tsx",
      "pageType": "collection page"
    },
    {
      "__resolveType": "site/sections/Rolex/BreadCrumb.tsx",
      "breadcrumbs": [
        {
          "href": "/rolex/relogios-rolex",
          "label": "Relógios Rolex"
        },
        {
          "label": "Day-Date",
          "href": "/rolex/watches/day-date"
        }
      ]
    },
    {
      "__resolveType": "site/sections/Rolex/Gallery.tsx",
      "hexa": "f9f7f4",
      "screen": "XL",
      "images": [
        {
          "desktop": "https://assets.decocache.com/dryzunstore/b7f09826-cfa4-4fd6-8a30-721f6a2280f3/rolex-day-date-cover-m228235-0055_2402jva_001-landscape.jpg",
          "mobile": "https://assets.decocache.com/dryzunstore/15906cb6-44f2-4d12-ab2f-cd8f86ef9c7e/rolex-day-date-cover-m228235-0055_2402jva_001_portrait.jpg",
          "alt": "relógios rolex Day-Date – Dryzun"
        }
      ],
      "paddingTop": false,
      "paddingBottom": false
    },
    {
      "__resolveType": "site/sections/Rolex/Text.tsx",
      "hexa": "fff",
      "screen": "L",
      "paddingTop": true,
      "paddingBottom": true,
      "title": "<p><strong><span style=\"font-size: 29pt\">A realização de um ideal</span></strong></p>",
      "isColumns": true,
      "text": "<p><strong>Quando chega a meia-noite, o Oyster Perpetual Day-Date forma uma ponte entre o passado e o futuro, entre o que foi alcançado e o que resta a ser vivido. </strong>Desde 1956, o modelo testemunhou os maiores momentos da história no pulso de visionários, virtuosos e pioneiros. Aqueles que transformam cada dia em uma promessa para o futuro.</p>",
      "subtitle": "<h1><strong><span style=\"font-size: 29pt\">Rolex Day-Date</span></strong></h1>",
      "NotisH1": true
    },
    {
      "__resolveType": "website/sections/Rendering/Lazy.tsx",
      "section": {
        "__resolveType": "VITRINE DAYDATE"
      }
    },
    {
      "__resolveType": "site/sections/Rolex/Video.tsx",
      "screen": "L",
      "hexa": "fff",
      "paddingTop": false,
      "paddingBottom": false,
      "url": "https://www.youtube.com/embed/WIIDLPQNIMs?si=RXC-ZiQw7y2F7KLw"
    },
    {
      "__resolveType": "site/sections/Rolex/Text.tsx",
      "screen": "S",
      "hexa": "fff",
      "paddingTop": true,
      "paddingBottom": true,
      "title": "<p><strong>O Day-Date é o relógio de um mundo globalizado, multicultural e em constante evolução.</strong></p>",
      "isColumns": false,
      "text": "<p><br>Quando foi lançado, em 1956, o Day-Date representou uma inovação importante: foi o primeiro relógio de pulso com calendário a indicar, em complemento à data, o dia da semana por extenso, em uma abertura semicircular às 12 h&nbsp;– uma verdadeira proeza técnica na época. Fabricado exclusivamente em metal precioso&nbsp;– ouro amarelo, branco ou Everose 18 quilates, ou ainda platina 950&nbsp;– e acompanhado de sua emblemática pulseira President, seus inúmeros mostradores fazem dele um símbolo da autoexpressão.</p>",
      "NotisH1": true
    },
    {
      "__resolveType": "site/sections/Rolex/Gallery.tsx",
      "screen": "M",
      "hexa": "f9f7f4",
      "paddingTop": true,
      "images": [
        {
          "desktop": "https://assets.decocache.com/dryzunstore/304bf870-3bec-4f6f-ad6c-015296694117/rolex-day-date-m128345rbr_0068_2311jva_001-m228238-0066_2401jva_001-landscape.jpeg",
          "mobile": "https://assets.decocache.com/dryzunstore/a84ed6fc-df11-4f1e-a8d3-79ecc22cf29b/rolex-day-date-m128345rbr_0068_2311jva_001-m228238-0066_2401jva_001-portrait.jpeg",
          "alt": "DAY-DATE"
        }
      ]
    },
    {
      "__resolveType": "site/sections/Rolex/Text.tsx",
      "screen": "S",
      "hexa": "f9f7f4",
      "paddingTop": true,
      "title": "<p><strong>O Day-Date fala o idioma do usuário</strong></p>",
      "isColumns": false,
      "paddingBottom": true,
      "text": "<p><br>Embora os dias possam ser os mesmos em qualquer lugar do mundo, eles são escritos de forma diferente dependendo do idioma. Usando a maioria dos sistemas de escrita&nbsp;– ideogramas latinos, árabes, cirílicos, hebraicos, japoneses, chineses e até mesmo o alfassilabário ge’ez usado no Chifre da África –, o Day-Date expressa a identidade cultural de seu usuário. Disponível em 26 idiomas, ele é um verdadeiro relógio internacional, universal e pessoal.</p>",
      "NotisH1": true
    },
    {
      "__resolveType": "site/sections/Rolex/Gallery.tsx",
      "screen": "XL",
      "hexa": "f9f7f4",
      "paddingTop": false,
      "images": [
        {
          "desktop": "https://assets.decocache.com/dryzunstore/c61e5199-facc-48fe-9550-8928b697c960/rolex-day-date-m128348rbr-0049_2301jva_003-landscape.jpeg",
          "mobile": "https://assets.decocache.com/dryzunstore/8fdd81d7-5ce3-4353-8684-6ae82ddf6ae1/rolex-day-date-m128348rbr-0049_2301jva_003_portrait.jpeg",
          "alt": "GMT-Master II"
        }
      ]
    },
    {
      "__resolveType": "site/sections/Rolex/Gallery.tsx",
      "screen": "M",
      "hexa": "fff",
      "paddingTop": true,
      "images": [
        {
          "desktop": "https://assets.decocache.com/dryzunstore/563cb5a5-ef5d-4565-8e1f-e18bcba1dcc9/rolex-day-date-m228238-0042_2304jva_001_v2_c-movt3255_a_2210uf_001-landscape.jpeg",
          "mobile": "https://assets.decocache.com/dryzunstore/4b71f522-225e-459b-8276-5eeaaf9967b6/rolex-day-date-m228238-0042_2304jva_001_v2_c-movt3255_a_2210uf_001_portrait.jpeg",
          "alt": "GMT-Master II"
        }
      ]
    },
    {
      "__resolveType": "site/sections/Rolex/Text.tsx",
      "screen": "S",
      "hexa": "fff",
      "paddingTop": true,
      "title": "<p><strong>O milagre da meia-noite</strong></p><p><strong>Um ideal de precisão</strong></p><p></p>",
      "isColumns": false,
      "paddingBottom": true,
      "text": "<p><br>Quando chega a meia-noite, o dia e a data mudam simultaneamente em suas respectivas aberturas no mostrador. Esta proeza relojoeira, o “milagre da meia-noite”, baseia-se em um mecanismo de discos. É fruto de vários anos de pesquisa: de 1950 a 1955, a Rolex registrou quatro patentes de relógios com indicação do dia e da data.</p><p><br>Atualmente, o Day-Date 40 é equipado com o calibre 3255, um mecanismo totalmente desenvolvido e manufaturado pela Rolex para garantir um desempenho superlativo.</p>",
      "NotisH1": true
    },
    {
      "__resolveType": "site/sections/Rolex/Gallery.tsx",
      "screen": "S",
      "hexa": "f9f7f4",
      "paddingTop": true,
      "images": [
        {
          "desktop": "https://assets.decocache.com/dryzunstore/8ca38cea-1a1e-41e8-963d-d775bca3bd0e/rolex-day-date-m228236-0012_2201ac_004-landscape.jpeg",
          "mobile": "https://assets.decocache.com/dryzunstore/61b58bcc-4e5e-4509-a7f3-066b94e6b6d3/rolex-day-date-m228236-0012_2201ac_004_portrait.jpeg",
          "alt": "GMT-MASTER II"
        }
      ]
    },
    {
      "__resolveType": "site/sections/Rolex/Text.tsx",
      "screen": "S",
      "hexa": "f9f7f4",
      "paddingTop": true,
      "title": "A pulseira President",
      "isColumns": false,
      "paddingBottom": true,
      "text": "<p><br>Criada especialmente para o lançamento do prestigioso relógio Oyster Perpetual Day-Date em 1956, a pulseira President de três fileiras, fabricada exclusivamente em ouro 18&nbsp;quilates ou em platina 950, é ainda hoje reservada para o Day-Date e para as versões do Datejust em metal precioso.</p>",
      "NotisH1": true
    },
    {
      "__resolveType": "site/sections/Rolex/Gallery.tsx",
      "screen": "M",
      "hexa": "fff",
      "paddingTop": true,
      "images": [
        {
          "desktop": "https://assets.decocache.com/dryzunstore/92a47290-24ca-4abf-a8d7-29e92d6b849b/rolex-day-date-m128238-0045_20jva-m228238-0061_2207dh_001-landscape.jpeg",
          "mobile": "https://assets.decocache.com/dryzunstore/e7626b20-6acd-45fb-9c83-1089ec8e968b/rolex-day-date-m128238-0045_20jva-m228238-0061_2207dh_001_portrait.jpeg",
          "alt": "GMT-MASTER II"
        }
      ]
    },
    {
      "__resolveType": "site/sections/Rolex/Text.tsx",
      "screen": "S",
      "hexa": "fff",
      "paddingTop": true,
      "title": "Um precioso aliado",
      "isColumns": false,
      "paddingBottom": true,
      "text": "<p><br>Usado ao longo do tempo por personalidades políticas, líderes e visionários do mundo inteiro, o Day-Date é imediatamente reconhecível no pulso, notadamente graças à sua emblemática pulseira President. Um nome predestinado que, somado à grandeza das personalidades que o utilizaram, rendeu ao Day-Date o apelido de “Relógio dos Presidentes”.<br><br>Décadas vêm e vão, mas o Day-Date permanece onde sempre esteve&nbsp;– na vanguarda da modernidade. Um relógio magistral e fruto do know-how da Rolex, o Day-Date acompanha as personalidades que moldam o mundo em suas respectivas disciplinas por meio de seu compromisso, qualidades humanas e espírito criativo.<br><br>Entre os Embaixadores Rolex associados ao Day-Date, a marca conta com a esquiadora norte-americana Lindsey Vonn, o tenista suíço Roger Federer, o cineasta norte-americano Martin Scorsese e os golfistas Arnold Palmer, Jack Nicklaus e Gary Player.</p>",
      "NotisH1": true
    },
    {
      "__resolveType": "site/sections/Rolex/Gallery.tsx",
      "screen": "XL",
      "hexa": "f9f7f4",
      "paddingTop": false,
      "images": [
        {
          "desktop": "https://assets.decocache.com/dryzunstore/a6f59c21-9eea-4bdb-ad0d-cfe840ab3492/rolex-day-date-10058_rsa_cad24_everose_np24_caraibes_bs1-landscape.jpeg",
          "mobile": "https://assets.decocache.com/dryzunstore/d096c7e1-61e3-4ddf-98c9-eb2f85198ae0/rolex-day-date-10058_rsa_cad24_everose_np24_caraibes_bs1_portrait.jpeg",
          "alt": "GMT-MASTER II"
        }
      ]
    },
    {
      "__resolveType": "website/sections/Rendering/Lazy.tsx",
      "section": {
        "__resolveType": "site/sections/Rolex/Exploring2024.tsx"
      }
    },
    {
      "__resolveType": "site/sections/Rolex/BackToTopRolex.tsx"
    },
    {
      "__resolveType": "Footer - 01"
    },
    {
      "__resolveType": "site/sections/Dryzun/DataStructured.tsx",
      "data": "{\n   \"@context\":\"https://schema.org/\",\n   \"@graph\":[\n      {\n         \"@type\":\"BreadcrumbList\",\n         \"itemListElement\":[\n            {\n               \"@type\":\"ListItem\",\n               \"position\":1,\n               \"name\":\"Página Inicial\",\n               \"item\":\"https://www.dryzun.com.br\"\n            },\n            {\n               \"@type\":\"ListItem\",\n               \"position\":2,\n               \"name\":\"Joias\",\n               \"item\":\"https://www.dryzun.com.br/joias\"\n            },\n            {\n               \"@type\":\"ListItem\",\n               \"position\":3,\n               \"name\":\"Rolex\",\n               \"item\":\"https://www.dryzun.com.br/rolex\"\n            },\n            {\n               \"@type\":\"ListItem\",\n               \"position\":3,\n               \"name\":\"Relógios Tudor\",\n               \"item\":\"https://www.dryzun.com.br/tudor/colecao\"\n            },\n            {\n               \"@type\":\"ListItem\",\n               \"position\":5,\n               \"name\":\"Relógios\",\n               \"item\":\"https://www.dryzun.com.br/relogios\"\n            },\n            {\n               \"@type\":\"ListItem\",\n               \"position\":6,\n               \"name\":\"Canetas\",\n               \"item\":\"https://www.dryzun.com.br/canetas\"\n            },\n            {\n               \"@type\":\"ListItem\",\n               \"position\":6,\n               \"name\":\"Presentes\",\n               \"item\":\"https://www.dryzun.com.br/presentes\"\n            },\n            {\n               \"@type\":\"ListItem\",\n               \"position\":6,\n               \"name\":\"Casamento\",\n               \"item\":\"https://www.dryzun.com.br/casamento\"\n            }\n         ]\n      },\n      {\n         \"@type\":\"JewelryStore\",\n         \"name\":\"Dryzun\",\n         \"image\":\"https://ozksgdmyrqcxcwhnbepg.supabase.co/storage/v1/object/public/assets/9049/626da8eb-e46e-4e2b-b4cf-3a67d209df01\",\n         \"@id\":\"\",\n         \"url\":\"https://www.dryzun.com.br\",\n         \"telephone\":\"5511993847911\",\n         \"priceRange\":\"$$$$\",\n         \"address\":{\n            \"@type\":\"PostalAddress\",\n            \"streetAddress\":\"Avenida Brigadeiro Faria Lima, 2232\",\n            \"addressLocality\":\"São Paulo\",\n            \"postalCode\":\"01451-000\",\n            \"addressCountry\":\"BR\"\n         },\n         \"geo\":{\n            \"@type\":\"GeoCoordinates\",\n            \"latitude\":-23.576779,\n            \"longitude\":-46.68768\n         },\n         \"openingHoursSpecification\":{\n            \"@type\":\"OpeningHoursSpecification\",\n            \"dayOfWeek\":[\n               \"Monday\",\n               \"Tuesday\",\n               \"Wednesday\",\n               \"Thursday\",\n               \"Friday\",\n               \"Saturday\"\n            ],\n            \"opens\":\"10:00\",\n            \"closes\":\"21:30\"\n         },\n         \"sameAs\":[\n            \"https://www.facebook.com/Dryzun/\",\n            \"https://www.instagram.com/dryzunjoias/\",\n            \"https://www.youtube.com/user/dryzunjoias\"\n         ]\n      },\n      {\n         \"@type\":\"Organization\",\n         \"name\":\"Dryzun\",\n         \"url\":\"https://www.dryzun.com.br\",\n         \"logo\":\"https://ozksgdmyrqcxcwhnbepg.supabase.co/storage/v1/object/public/assets/9049/626da8eb-e46e-4e2b-b4cf-3a67d209df01\",\n         \"sameAs\":[\n            \"https://www.facebook.com/Dryzun/\",\n            \"https://www.instagram.com/dryzunjoias/\",\n            \"https://www.youtube.com/user/dryzunjoias\"\n         ]\n      }\n   ]\n}"
    },
    {
      "__resolveType": "site/sections/ServerAnalytics.tsx"
    },
    {
      "__resolveType": "site/sections/CookieDryzun.tsx"
    }
  ],
  "seo": {
    "__resolveType": "website/sections/Seo/SeoV2.tsx",
    "type": "website",
    "title": "Rolex Day-Date | Dryzun",
    "description": "Conheça os Relógios Rolex Day-Date no site da Dryzun, uma distribuidora oficial Rolex. Descubra mais na Dryzun.",
    "favicon": "https://assets.decocache.com/dryzunstore/6849c44d-ca2c-43c9-b95f-ae39b8657400/1742482897359-9ebbd7c1-20c9-4de7-881f-07d86922101c",
    "image": "https://assets.decocache.com/dryzunstore/1c5fd4bf-eb28-4bc2-a5ed-e9d418330235/1742482898690-97d0c537-a23b-4628-bb4d-30f64ca606e2",
    "canonical": "https://www.dryzun.com.br/rolex/day-date"
  },
  "__resolveType": "website/pages/Page.tsx"
}