{
  "name": "Search",
  "path": "/s",
  "sections": [
    {
      "__resolveType": "site/sections/Dryzun/TagCanonical.tsx"
    },
    {
      "__resolveType": "website/sections/Seo/Seo.tsx",
      "type": "website",
      "titleTemplate": "%s | Deco.cx",
      "descriptionTemplate": "%s | Deco.cx",
      "image": "https://deco-sites-assets.s3.sa-east-1.amazonaws.com/dryzunstore/0fd7ba94-1890-4b7c-8187-6c411c939089/logo--dryzun.png",
      "favicon": "https://deco-sites-assets.s3.sa-east-1.amazonaws.com/dryzunstore/70d0ff59-3034-4e8d-8ed5-ee4440291e66/dryzun-favicon.webp"
    },
    {
      "__resolveType": "Header - 01"
    },
    {
      "__resolveType": "site/sections/Product/SearchResult.tsx",
      "page": {
        "__resolveType": "PLP Loader"
      },
      "layout": {
        "columns": {
          "mobile": 2,
          "desktop": 4
        },
        "variant": "aside"
      }
    },
    {
      "__resolveType": "Footer - 01"
    }
  ],
  "__resolveType": "website/pages/Page.tsx"
}